{"id":"app1.css","dependencies":[{"name":"H:\\codeWork\\HtmlProject\\MVC-demo\\package.json","includedInParent":true,"mtime":1666359411136},{"name":"_css_loader","parent":"H:\\codeWork\\HtmlProject\\MVC-demo\\src\\app1.css","resolved":"C:\\Users\\long\\AppData\\Local\\Yarn\\Data\\global\\node_modules\\parcel\\src\\builtins\\css-loader.js"}],"generated":{"css":"#app1 {\r\n    border: 1px solid #000;\r\n}\r\n\r\n#app1 .output {\r\n}\r\n\r\n#app1 .actions {\r\n}","js":"\nvar reloadCSS = require('_css_loader');\nmodule.hot.dispose(reloadCSS);\nmodule.hot.accept(reloadCSS);"},"hash":"eb39c020a66a15792c423ce539c10613","cacheData":{"env":{}}}